{"data":{"site":{"siteMetadata":{"subtitle":"Learning frontend, together","title":"Awesome Learning","url":"https://wayfair.github.io/awesome-learning/"}},"markdownRemark":{"id":"62ded412-6c59-575f-ae39-7bac6a886884","html":"","fields":{"slug":"/courses/Functions-and-Scope/context-and-arrows","tagSlugs":["/tag/a-tag/"]},"frontmatter":{"title":"Context and Arrows","preReadQuiz":null}}},"pageContext":{"isCreatedByStatefulCreatePages":false,"slug":"/courses/Functions-and-Scope/context-and-arrows"}}